MANIFEST.in
README.md
setup.cfg
setup.py
clearsale/__init__.py
clearsale/api.py
clearsale/responses.py
clearsale.egg-info/PKG-INFO
clearsale.egg-info/SOURCES.txt
clearsale.egg-info/dependency_links.txt
clearsale.egg-info/requires.txt
clearsale.egg-info/top_level.txt
clearsale/entities/__init__.py
clearsale/entities/base.py
clearsale/entities/billing_data.py
clearsale/entities/common.py
clearsale/entities/item.py
clearsale/entities/order.py
clearsale/entities/payment.py
clearsale/entities/shipping_data.py