Metadata-Version: 1.1
Name: clearsale
Version: 0.1
Summary: Python library to use ClearSale Total Anti Fraud
Home-page: https://github.com/mateuspadua/clearsale-python
Author: Mateus Vanzo de Padua
Author-email: mateuspaduaweb@gmail.com
License: MIT License
Keywords: clearsale,antifraude,anti,fraude,python
Platform: OS Independent
Classifier: Framework :: Django
Classifier: Intended Audience :: Developers
Classifier: License :: OSI Approved :: MIT License
Classifier: Operating System :: OS Independent
Classifier: Topic :: Software Development
Classifier: Programming Language :: Python
Classifier: Programming Language :: Python :: 2
